nslog.py
std_nslog-1.0.2.dist-info/LICENSE
std_nslog-1.0.2.dist-info/METADATA
std_nslog-1.0.2.dist-info/WHEEL
std_nslog-1.0.2.dist-info/top_level.txt
std_nslog-1.0.2.dist-info/RECORD
