Metadata-Version: 2.1
Name: std-nslog
Version: 1.0.2
Summary: A shim that redirects stderr/stdout to the Apple System Log (NSLog)
Home-page: https://github.com/beeware/std-nslog
Author: Russell Keith-Magee
Author-email: russell@keith-magee.com
Maintainer: Russell Keith-Magee
Maintainer-email: russell@keith-magee.com
License: New BSD
Project-URL: Funding, https://beeware.org/contributing/membership/
Project-URL: Tracker, https://github.com/beeware/std-nslog/issues
Project-URL: Source, https://github.com/beeware/std-nslog
Keywords: apple,nslog,system log,macOS,iOS
Platform: any
Classifier: Development Status :: 5 - Production/Stable
Classifier: Intended Audience :: Developers
Classifier: License :: OSI Approved :: BSD License
Classifier: Operating System :: iOS
Classifier: Operating System :: MacOS :: MacOS X
Classifier: Programming Language :: Python :: 3
Classifier: Programming Language :: Python :: 3.7
Classifier: Programming Language :: Python :: 3.8
Classifier: Programming Language :: Python :: 3.9
Classifier: Programming Language :: Python :: 3.10
Classifier: Programming Language :: Python :: 3.11
Classifier: Programming Language :: Python :: 3.12
Classifier: Programming Language :: Python :: 3 :: Only
Classifier: Topic :: Software Development
Classifier: Topic :: Utilities
Requires-Python: >=3.7
License-File: LICENSE
